skill_instructions/LICENSE.md
skill_instructions/README.md
skill_instructions/__init__.py
skill_instructions/instruction_checks.py
skill_instructions/skill.json
skill_instructions/version.py
skill_instructions/locale/en-us/cancel.voc
skill_instructions/locale/en-us/choose.dialog
skill_instructions/locale/en-us/file_exists.dialog
skill_instructions/locale/en-us/finished.dialog
skill_instructions/locale/en-us/instruction_names.dialog
skill_instructions/locale/en-us/instructions_keyword.voc
skill_instructions/locale/en-us/neon.voc
skill_instructions/locale/en-us/no.voc
skill_instructions/locale/en-us/no_file.dialog
skill_instructions/locale/en-us/no_instruction.dialog
skill_instructions/locale/en-us/repeat.dialog
skill_instructions/locale/en-us/run_instructions.intent
skill_instructions/locale/en-us/start.dialog
skill_instructions/locale/en-us/yes.voc
skill_instructions/locale/pl-pl/choose.dialog
skill_instructions/locale/pl-pl/file_exists.dialog
skill_instructions/locale/pl-pl/finished.dialog
skill_instructions/locale/pl-pl/instruction_names.dialog
skill_instructions/locale/pl-pl/instructions_keyword.voc
skill_instructions/locale/pl-pl/neon.voc
skill_instructions/locale/pl-pl/no_file.dialog
skill_instructions/locale/pl-pl/no_instruction.dialog
skill_instructions/locale/pl-pl/repeat.dialog
skill_instructions/locale/pl-pl/run_instructions.intent
skill_instructions/locale/pl-pl/start.dialog
skill_instructions/locale/pl-pl/yes.voc
skill_instructions/locale/uk-uk/choose.dialog
skill_instructions/locale/uk-uk/file_exists.dialog
skill_instructions/locale/uk-uk/finished.dialog
skill_instructions/locale/uk-uk/instruction_names.dialog
skill_instructions/locale/uk-uk/instructions_keyword.voc
skill_instructions/locale/uk-uk/neon.voc
skill_instructions/locale/uk-uk/no_file.dialog
skill_instructions/locale/uk-uk/no_instruction.dialog
skill_instructions/locale/uk-uk/repeat.dialog
skill_instructions/locale/uk-uk/run_instructions.intent
skill_instructions/locale/uk-uk/start.dialog
skill_instructions/neon_skill_instructions.egg-info/PKG-INFO
skill_instructions/neon_skill_instructions.egg-info/SOURCES.txt
skill_instructions/neon_skill_instructions.egg-info/dependency_links.txt
skill_instructions/neon_skill_instructions.egg-info/entry_points.txt
skill_instructions/neon_skill_instructions.egg-info/requires.txt
skill_instructions/neon_skill_instructions.egg-info/top_level.txt
neon_skill_instructions-1.0.0.dist-info/LICENSE.md
neon_skill_instructions-1.0.0.dist-info/METADATA
neon_skill_instructions-1.0.0.dist-info/WHEEL
neon_skill_instructions-1.0.0.dist-info/entry_points.txt
neon_skill_instructions-1.0.0.dist-info/top_level.txt
neon_skill_instructions-1.0.0.dist-info/RECORD
