Metadata-Version: 2.1
Name: neon-skill-instructions
Version: 1.0.0
Home-page: https://github.com/NeonGeckoCom/skill-instructions
Author: Neongecko
Author-email: developers@neon.ai
License: BSD-3-Clause
License-File: LICENSE.md
Requires-Dist: numpy
Requires-Dist: wavfile
Requires-Dist: neon-utils~=1.12
Requires-Dist: ovos-utils>=0.0.28,~=0.0
Requires-Dist: ovos-workshop>=0.0.15,~=0.0
Requires-Dist: word2number
Provides-Extra: test
Requires-Dist: neon-minerva[padatious]~=0.2; extra == "test"
